{
  "public": {
    "author": "evan GmbH",
    "dapp": {
      "dependencies": {},
      "entrypoint": "materialicons.libs.js",
      "files": [
        "materialicons.libs.css",
        "materialicons.libs.js"
      ],
      "origin": "QmY75UyjXKsFL3SfY34vFCTmpNyzKbTwHHRe76x4pUff6j",
      "primaryColor": "",
      "secondaryColor": "#f9f9ff",
      "standalone": false,
      "type": "cached-dapp"
    },
    "dbcpVersion": 2,
    "description": "",
    "i18n": {
      "description": {
        "en": ""
      },
      "name": {
        "en": "materialicons.libs"
      }
    },
    "imgSquare": "",
    "name": "materialicons.libs",
    "tags": [
      "dapp",
      "evan",
      "library"
    ],
    "version": "4.5.0",
    "versions": {
      "1.8.36": "QmdocVBKgt9zDeNU2CBP6m9gR8vWtPH9ehNuQkEEUeW8AN",
      "4.4.0": "QmWadpx9RE982ZosokU3KVmEZWc7DyCmGNSh97SxbNMnwc",
      "4.5.0": "QmWhZFexWBdgEmHthi6B21D4rDtyx9QS8NrPoFAdBwBhg3"
    }
  }
}